{
  "unversionedId": "getting-started/prerequisites",
  "id": "version-v13.0.0/getting-started/prerequisites",
  "isDocsHomePage": false,
  "title": "Prerequisites",
  "description": "Prerequisites for setting up Relay",
  "source": "@site/versioned_docs/version-v13.0.0/getting-started/prerequisites.md",
  "sourceDirName": "getting-started",
  "slug": "/getting-started/prerequisites/",
  "permalink": "/docs/getting-started/prerequisites/",
  "editUrl": "https://github.com/facebook/relay/tree/main/website/versioned_docs/version-v13.0.0/getting-started/prerequisites.md",
  "tags": [],
  "version": "v13.0.0",
  "lastUpdatedBy": "Author",
  "lastUpdatedAt": 1539502055,
  "formattedLastUpdatedAt": "10/14/2018",
  "frontMatter": {
    "id": "prerequisites",
    "title": "Prerequisites",
    "slug": "/getting-started/prerequisites/",
    "description": "Prerequisites for setting up Relay",
    "keywords": [
      "prerequisites"
    ]
  },
  "sidebar": "version-v13.0.0/docs",
  "previous": {
    "title": "Introduction to Relay",
    "permalink": "/docs/"
  },
  "next": {
    "title": "Installation and Setup",
    "permalink": "/docs/getting-started/installation-and-setup/"
  }
}